drf_elastic_filter/__init__.py
drf_elastic_filter/elastic_filter.py
drf_elastic_filter/utils.py
drf_elastic_filter-1.0.2.dist-info/LICENSE
drf_elastic_filter-1.0.2.dist-info/METADATA
drf_elastic_filter-1.0.2.dist-info/WHEEL
drf_elastic_filter-1.0.2.dist-info/top_level.txt
drf_elastic_filter-1.0.2.dist-info/RECORD
