Metadata-Version: 2.1
Name: drf-elastic-filter
Version: 1.0.2
Summary: DRF Elastic Filter for Models
Home-page: https://github.com/realsaeedhassani/drf_elastic_filter
Author: Saeed Hassani Borzadaran
Author-email: hassanisaeed19@gmail.com
License: UNKNOWN
Project-URL: Bug Tracker, https://github.com/realsaeedhassani/drf_elastic_filter/issues/new
Platform: UNKNOWN
Classifier: Programming Language :: Python :: 3
Classifier: License :: OSI Approved :: MIT License
Classifier: Operating System :: OS Independent
Requires-Python: >=3.6
License-File: LICENSE
Requires-Dist: Django (>=2.2)
